cleanstr/Functions.py
cleanstr/__init__.py
cleanstr-0.1.dist-info/METADATA
cleanstr-0.1.dist-info/WHEEL
cleanstr-0.1.dist-info/licenses/LICENSE
cleanstr-0.1.dist-info/RECORD
