Metadata-Version: 2.1
Name: cleanstr
Version: 0.1
Summary: Python Package for Strings Cleaning
Project-URL: Homepage, https://github.com/pypa/cleanstr
Project-URL: Bug Tracker, https://github.com/pypa/cleanstr/issues
Author-email: Ashwini Maurya <akmaurya07@gmail.com>
License-File: LICENSE
Classifier: License :: OSI Approved :: MIT License
Classifier: Operating System :: OS Independent
Classifier: Programming Language :: Python :: 3
Requires-Python: >=3.7
